_d/__init__.py
randomuagents/__init__.py
randomuagents/_d/__init__.py
randomuagents-1.0.6.dist-info/LICENSE
randomuagents-1.0.6.dist-info/METADATA
randomuagents-1.0.6.dist-info/WHEEL
randomuagents-1.0.6.dist-info/top_level.txt
randomuagents-1.0.6.dist-info/RECORD
