Metadata-Version: 2.1
Name: randomuagents
Version: 1.0.6
Summary: Library for fetching random user agents based on device type (desktop, mobile, etc.).
Home-page: https://github.com/70L0-0j0/randomuagents
Author: 70L0-0j0
Author-email: 70L0-0j0@lamia.xyz
Classifier: Programming Language :: Python :: 3
Classifier: License :: OSI Approved :: MIT License
Classifier: Operating System :: OS Independent
Requires-Python: >=3.6
License-File: LICENSE
